cdk_lex_zip_import/__init__.py
cdk_lex_zip_import/py.typed
cdk_lex_zip_import/_jsii/__init__.py
cdk_lex_zip_import/_jsii/cdk-lex-zip-import@0.0.90.jsii.tgz
cdk_lex_zip_import-0.0.90.dist-info/LICENSE
cdk_lex_zip_import-0.0.90.dist-info/METADATA
cdk_lex_zip_import-0.0.90.dist-info/WHEEL
cdk_lex_zip_import-0.0.90.dist-info/top_level.txt
cdk_lex_zip_import-0.0.90.dist-info/RECORD
