Metadata-Version: 2.1
Name: cdk-lex-zip-import
Version: 0.0.90
Summary: cdk construct for importing a zipped Lex bot
Home-page: https://github.com/schuettc/cdk-lex-zip-import.git
Author: Court Schuett<schuettc@amazon.com>
License: Apache-2.0
Project-URL: Source, https://github.com/schuettc/cdk-lex-zip-import.git
Classifier: Intended Audience :: Developers
Classifier: Operating System :: OS Independent
Classifier: Programming Language :: JavaScript
Classifier: Programming Language :: Python :: 3 :: Only
Classifier: Programming Language :: Python :: 3.8
Classifier: Programming Language :: Python :: 3.9
Classifier: Programming Language :: Python :: 3.10
Classifier: Programming Language :: Python :: 3.11
Classifier: Typing :: Typed
Classifier: Development Status :: 5 - Production/Stable
Classifier: License :: OSI Approved
Requires-Python: ~=3.8
License-File: LICENSE
Requires-Dist: aws-cdk-lib <3.0.0,>=2.20.0
Requires-Dist: constructs <11.0.0,>=10.0.5
Requires-Dist: jsii <2.0.0,>=1.94.0
Requires-Dist: publication >=0.0.3
Requires-Dist: typeguard ~=2.13.3
